[
  {
    "id": 1,
    "expense": "Court Fee",
    "by": 1,
    "amount": 45,
    "date": "2020-01-01",
    "applies": [
      1,
      2,
      3
    ],
    "type": "debit"
  },
  {
    "id": 2,
    "expense": "Shuttle Cocks",
    "by": 1,
    "amount": 33,
    "date": "2020-01-01",
    "applies": [
      0,
      1,
      2,
      3
    ],
    "type": "debit"
  },
  {
    "id": 3,
    "expense": "Fund Topup",
    "by": 4,
    "amount": 100,
    "date": "28-10-2024",
    "applies": [
      4
    ],
    "type": "credit"
  },
  {
    "id": 4,
    "expense": "Fund Topup",
    "by": 5,
    "amount": 50,
    "date": "28-10-2024",
    "applies": [
      5
    ],
    "type": "credit"
  },
  {
    "id": 5,
    "expense": "Court Booking Fee",
    "by": 0,
    "amount": 28.08,
    "date": "28-10-2024",
    "applies": [
      3,
      1,
      5,
      7
    ],
    "type": "debit"
  },
  {
    "id": 6,
    "expense": "Dasaradhy Topup",
    "by": 3,
    "amount": 100,
    "date": "08-11-2024",
    "applies": [
      3
    ],
    "type": "credit"
  },
  {
    "id": 7,
    "expense": "Aravind Topup",
    "by": 9,
    "amount": 23.90,
    "date": "11-11-2024",
    "applies": [
      9
    ],
    "type": "credit"
  },
  {
  "id": 8,
  "expense": "Swap Sravan and Likith",
  "by": 4,
  "amount": 7.02,
  "date": "11-11-2024",
  "applies": [
    1
  ],
  "type": "credit"
},
  {
    "id": 9,
    "expense": "Swap Sravan and Likith",
    "by": 4,
    "amount": 7.02,
    "date": "11-11-2024",
    "applies": [
      4
    ],
    "type": "debit"
  },
  {
    "id": 10,
    "expense": "Shuttle Cocks Purchase",
    "by": 7,
    "amount": 40,
    "date": "11-11-2024",
    "applies": [
      0,1,2,3,4,5,6,7,8,9,10
    ],
    "type": "debit"
  },
  {
    "id": 11,
    "expense": "Topup Sunil Pending Amount",
    "by": 7,
    "amount": 36.7,
    "date": "11-11-2024",
    "applies": [
      7
    ],
    "type": "credit"
  }





]